autoactive/__init__.py
autoactive/toolboxinfo.py
autoactive/archive/__init__.py
autoactive/archive/dataobject.py
autoactive/archive/fileobject.py
autoactive/autoactive/__init__.py
autoactive/autoactive/archivereader.py
autoactive/autoactive/archivewriter.py
autoactive/autoactive/datatable.py
autoactive/autoactive/folder.py
autoactive/autoactive/session.py
autoactive/autoactive/source.py
autoactive/datastructures/__init__.py
autoactive/datastructures/fileinfo.py
autoactive/datastructures/meta.py
autoactive/datastructures/user.py
autoactive/datastructures/video.py
autoactive-0.2.0.dist-info/LICENSE.txt
autoactive-0.2.0.dist-info/METADATA
autoactive-0.2.0.dist-info/WHEEL
autoactive-0.2.0.dist-info/top_level.txt
autoactive-0.2.0.dist-info/RECORD
