Metadata-Version: 2.1
Name: autoactive
Version: 0.2.0
Summary: Module for reading and writing aaz files
Home-page: https://github.com/SINTEF/AutoActive-Python-toolbox.git
Author: Kasper Botker
Author-email: kasper.botker@sintef.no
License: Apache License Version 2.0
Platform: UNKNOWN
Classifier: Development Status :: 3 - Alpha
Classifier: Programming Language :: Python :: 3.8
Classifier: Programming Language :: Python :: 3.9
Classifier: Programming Language :: Python :: 3.10
Requires-Python: >=3.8
License-File: LICENSE.txt
Requires-Dist: numpy
Requires-Dist: pandas
Requires-Dist: pyarrow
